google_datacatalog_qlik_connector-0.1.2-py3.6-nspkg.pth
google/datacatalog_connectors/qlik/__init__.py
google/datacatalog_connectors/qlik/qlik2datacatalog_cli.py
google/datacatalog_connectors/qlik/prepare/__init__.py
google/datacatalog_connectors/qlik/prepare/assembled_entry_factory.py
google/datacatalog_connectors/qlik/prepare/constants.py
google/datacatalog_connectors/qlik/prepare/datacatalog_entry_factory.py
google/datacatalog_connectors/qlik/prepare/datacatalog_tag_factory.py
google/datacatalog_connectors/qlik/prepare/datacatalog_tag_template_factory.py
google/datacatalog_connectors/qlik/prepare/dynamic_properties_helper.py
google/datacatalog_connectors/qlik/prepare/entry_relationship_mapper.py
google/datacatalog_connectors/qlik/scrape/__init__.py
google/datacatalog_connectors/qlik/scrape/authenticator.py
google/datacatalog_connectors/qlik/scrape/base_engine_api_helper.py
google/datacatalog_connectors/qlik/scrape/constants.py
google/datacatalog_connectors/qlik/scrape/engine_api_dimensions_helper.py
google/datacatalog_connectors/qlik/scrape/engine_api_measures_helper.py
google/datacatalog_connectors/qlik/scrape/engine_api_scraper.py
google/datacatalog_connectors/qlik/scrape/engine_api_sheets_helper.py
google/datacatalog_connectors/qlik/scrape/engine_api_visualizations_helper.py
google/datacatalog_connectors/qlik/scrape/metadata_scraper.py
google/datacatalog_connectors/qlik/scrape/repository_services_api_helper.py
google/datacatalog_connectors/qlik/scrape/websocket_replies_helper.py
google/datacatalog_connectors/qlik/scrape/websocket_responses_manager.py
google/datacatalog_connectors/qlik/sync/__init__.py
google/datacatalog_connectors/qlik/sync/metadata_synchronizer.py
google_datacatalog_qlik_connector-0.1.2.dist-info/METADATA
google_datacatalog_qlik_connector-0.1.2.dist-info/WHEEL
google_datacatalog_qlik_connector-0.1.2.dist-info/entry_points.txt
google_datacatalog_qlik_connector-0.1.2.dist-info/namespace_packages.txt
google_datacatalog_qlik_connector-0.1.2.dist-info/top_level.txt
google_datacatalog_qlik_connector-0.1.2.dist-info/RECORD
