Metadata-Version: 2.1
Name: google-datacatalog-qlik-connector
Version: 0.1.2
Summary: Package for ingesting Qlik metadata into Google Cloud Data Catalog
Home-page: UNKNOWN
Author: Google LLC
License: UNKNOWN
Platform: Posix; MacOS X; Windows
Classifier: Development Status :: 4 - Beta
Classifier: Natural Language :: English
Classifier: Programming Language :: Python
Classifier: Programming Language :: Python :: 3.6
Classifier: Programming Language :: Python :: 3.7
Requires-Dist: google-datacatalog-connectors-commons (~=0.6.8)
Requires-Dist: jmespath (~=0.10.0)
Requires-Dist: requests-ntlm (~=1.1.0)
Requires-Dist: websockets (~=8.1)
